modcma-1.2.0.dist-info/RECORD
modcma-1.2.0.dist-info/WHEEL
modcma-1.2.0.dist-info/top_level.txt
modcma-1.2.0.dist-info/METADATA
modcma-1.2.0.dist-info/licenses/LICENSE
modcma/modularcmaes.py
modcma/__init__.py
modcma/__main__.py
modcma/population.py
modcma/parameters.py
modcma/sampling.py
modcma/asktellcmaes.py
modcma/utils.py
modcma/c_maes/__init__.py
modcma/c_maes/cmaescpp.cpython-39-x86_64-linux-gnu.so
tests/test_c_criteria.py
tests/__init__.py
tests/test_modularcmaes.py
tests/test_parameters.py
tests/test_fmin.py
tests/test_population.py
tests/test_c_integer.py
tests/test_c_adaptation.py
tests/test_c_mutation.py
tests/test_asktellcmaes.py
tests/test_c_tuning.py
tests/test_sampling.py
tests/test_c_es.py
tests/test_c_selection.py
tests/create_expected.py
tests/test_utils.py
tests/test_c_bounds.py
tests/test_c_utils.py
tests/test_c_sampling.py
tests/test_c_population.py
