Metadata-Version: 2.4
Name: modcma
Version: 1.2.0
Summary: Package Containing Modular CMA-ES optimizer
Author: Jacob de Nobel
Author-email: jacobdenobel@gmail.com
Classifier: Programming Language :: Python :: 3
Classifier: License :: OSI Approved :: MIT License
Classifier: Operating System :: OS Independent
Requires-Python: >=3.8
License-File: LICENSE
Requires-Dist: configspace
Requires-Dist: numpy
Requires-Dist: scipy
Requires-Dist: ioh
Dynamic: author
Dynamic: author-email
Dynamic: classifier
Dynamic: description
Dynamic: description-content-type
Dynamic: license-file
Dynamic: requires-dist
Dynamic: requires-python
Dynamic: summary
